web2dataset/__init__.py
web2dataset/_nbdev.py
web2dataset/cleaner.py
web2dataset/cli.py
web2dataset/downloader.py
web2dataset/paralel.py
web2dataset/torch_dataset.py
web2dataset-0.1.0.dist-info/entry_points.txt
web2dataset-0.1.0.dist-info/WHEEL
web2dataset-0.1.0.dist-info/METADATA
web2dataset-0.1.0.dist-info/RECORD
