Metadata-Version: 2.1
Name: web2dataset
Version: 0.1.0
Summary: 
Author: sami jaghouar
Author-email: sami.jaghouar@hotmail.fr
Requires-Python: >=3.8,<4.0
Classifier: Programming Language :: Python :: 3
Classifier: Programming Language :: Python :: 3.10
Classifier: Programming Language :: Python :: 3.8
Classifier: Programming Language :: Python :: 3.9
Provides-Extra: torch
Requires-Dist: docarray (>=0.12.4,<0.13.0)
Requires-Dist: matplotlib (>=3.5.1,<4.0.0)
Requires-Dist: rich (>=12,<13)
Requires-Dist: selenium (>=4.1.0,<5.0.0)
Requires-Dist: torch (>=1.11.0,<2.0.0); extra == "torch"
Requires-Dist: torchvision (>=0.12.0,<0.13.0); extra == "torch"
Requires-Dist: typer (>=0.4.1,<0.5.0)
Requires-Dist: uuid (>=1.30,<2.0)
